PyDefold/__init__.py
PyDefold/bob-light.jar
PyDefold/input_ddf_pb2.py
PyDefold/input_ddf_pb2.pyi
PyDefold/particle_ddf_pb2.py
PyDefold/particle_ddf_pb2.pyi
PyDefold/rig_ddf_pb2.py
PyDefold/rig_ddf_pb2.pyi
PyDefold/ddf/__init__.py
PyDefold/ddf/ddf_extensions_pb2.py
PyDefold/ddf/ddf_extensions_pb2.pyi
PyDefold/ddf/ddf_math_pb2.py
PyDefold/ddf/ddf_math_pb2.pyi
PyDefold/engine/__init__.py
PyDefold/engine/engine_ddf_pb2.py
PyDefold/engine/engine_ddf_pb2.pyi
PyDefold/gameobject/__init__.py
PyDefold/gameobject/gameobject_ddf_pb2.py
PyDefold/gameobject/gameobject_ddf_pb2.pyi
PyDefold/gameobject/lua_ddf_pb2.py
PyDefold/gameobject/lua_ddf_pb2.pyi
PyDefold/gameobject/properties_ddf_pb2.py
PyDefold/gameobject/properties_ddf_pb2.pyi
PyDefold/gamesys/__init__.py
PyDefold/gamesys/atlas_ddf_pb2.py
PyDefold/gamesys/atlas_ddf_pb2.pyi
PyDefold/gamesys/buffer_ddf_pb2.py
PyDefold/gamesys/buffer_ddf_pb2.pyi
PyDefold/gamesys/camera_ddf_pb2.py
PyDefold/gamesys/camera_ddf_pb2.pyi
PyDefold/gamesys/gamesys_ddf_pb2.py
PyDefold/gamesys/gamesys_ddf_pb2.pyi
PyDefold/gamesys/gui_ddf_pb2.py
PyDefold/gamesys/gui_ddf_pb2.pyi
PyDefold/gamesys/label_ddf_pb2.py
PyDefold/gamesys/label_ddf_pb2.pyi
PyDefold/gamesys/mesh_ddf_pb2.py
PyDefold/gamesys/mesh_ddf_pb2.pyi
PyDefold/gamesys/model_ddf_pb2.py
PyDefold/gamesys/model_ddf_pb2.pyi
PyDefold/gamesys/physics_ddf_pb2.py
PyDefold/gamesys/physics_ddf_pb2.pyi
PyDefold/gamesys/sound_ddf_pb2.py
PyDefold/gamesys/sound_ddf_pb2.pyi
PyDefold/gamesys/sprite_ddf_pb2.py
PyDefold/gamesys/sprite_ddf_pb2.pyi
PyDefold/gamesys/texture_set_ddf_pb2.py
PyDefold/gamesys/texture_set_ddf_pb2.pyi
PyDefold/gamesys/tile_ddf_pb2.py
PyDefold/gamesys/tile_ddf_pb2.pyi
PyDefold/graphics/__init__.py
PyDefold/graphics/graphics_ddf_pb2.py
PyDefold/graphics/graphics_ddf_pb2.pyi
PyDefold/render/__init__.py
PyDefold/render/font_ddf_pb2.py
PyDefold/render/font_ddf_pb2.pyi
PyDefold/render/material_ddf_pb2.py
PyDefold/render/material_ddf_pb2.pyi
PyDefold/render/render_ddf_pb2.py
Pydefold-1.5.1.dist-info/METADATA
Pydefold-1.5.1.dist-info/WHEEL
Pydefold-1.5.1.dist-info/top_level.txt
Pydefold-1.5.1.dist-info/RECORD
