Metadata-Version: 2.1
Name: Pydefold
Version: 1.5.1
Summary: Python Package made by Mhadhbi Issam . 
Home-page: https://gitlab.com/game-dev-comapny/libraries/pydefold.git
Author: mhadhbixissam
Author-email: mhadhbixissam@gmail.com
Project-URL: Documentation, https://pydefold.readthedocs.io/en/latest/
Classifier: Programming Language :: Python :: 3
Classifier: License :: OSI Approved :: MIT License
Classifier: Operating System :: OS Independent
Requires-Dist: protobuf
